aspartik-0.1.0a3.dist-info/METADATA
aspartik-0.1.0a3.dist-info/WHEEL
aspartik-0.1.0a3.dist-info/licenses/LICENSE
aspartik.libs/libblas-9a624bcf.so.3
aspartik.libs/libgcc_s-2298274a.so.1
aspartik.libs/libgfortran-784919c5.so.5
aspartik.libs/liblapack-5cd0cf3f.so.3
aspartik.libs/libquadmath-33050579.so.0
aspartik/__init__.py
aspartik/_aspartik_rust_impl.cpython-312-x86_64-linux-musl.so
aspartik/_aspartik_rust_impl/_b3_rust_impl.pyi
aspartik/_aspartik_rust_impl/_data_rust_impl.pyi
aspartik/_aspartik_rust_impl/_io_rust_impl.pyi
aspartik/_aspartik_rust_impl/_rng_rust_impl.pyi
aspartik/_aspartik_rust_impl/_stats_rust_impl.pyi
aspartik/b3/__init__.py
aspartik/b3/__init__.pyi
aspartik/b3/clocks.py
aspartik/b3/loggers.py
aspartik/b3/operators/__init__.py
aspartik/b3/operators/_delta_exchange.py
aspartik/b3/operators/_node_slide.py
aspartik/b3/operators/_param_scale.py
aspartik/b3/operators/_tree_exchange.py
aspartik/b3/operators/_util.py
aspartik/b3/operators/_wilson_balding.py
aspartik/b3/priors/__init__.py
aspartik/b3/priors/_bound.py
aspartik/b3/priors/_distribution.py
aspartik/b3/substitutions.py
aspartik/b3/tree.py
aspartik/b3/tree.pyi
aspartik/data/__init__.py
aspartik/data/__init__.pyi
aspartik/io/__init__.py
aspartik/io/fasta.py
aspartik/io/fasta.pyi
aspartik/io/newick.py
aspartik/rng/__init__.py
aspartik/rng/__init__.pyi
aspartik/stats/__init__.py
aspartik/stats/distributions.py
aspartik/stats/distributions.pyi
aspartik-0.1.0a3.dist-info/RECORD
