Metadata-Version: 2.4
Name: aspartik
Version: 0.1.0a3
Classifier: Programming Language :: Rust
Classifier: Programming Language :: Python :: Implementation :: CPython
Classifier: Typing :: Typed
Classifier: Topic :: Scientific/Engineering
Classifier: Topic :: Scientific/Engineering :: Bio-Informatics
Classifier: Intended Audience :: Developers
Classifier: Intended Audience :: Science/Research
License-File: LICENSE
Summary: Computational biology toolkit
Keywords: bioinformatics
Author: Andrej Kolčin <self@kaathewise.net>
Author-email: Andrej Kolčin <self@kaathewise.net>
License: AGPL-3.0-only
Requires-Python: >=3.12
Project-URL: Source Code, https://github.com/kaathewisegit/aspartik
